aquatlantis_ori/__init__.py
aquatlantis_ori/client.py
aquatlantis_ori/const.py
aquatlantis_ori/device.py
aquatlantis_ori/exceptions.py
aquatlantis_ori/helpers.py
aquatlantis_ori/models.py
aquatlantis_ori/py.typed
aquatlantis_ori/http/__init__.py
aquatlantis_ori/http/client.py
aquatlantis_ori/http/const.py
aquatlantis_ori/http/exceptions.py
aquatlantis_ori/http/models.py
aquatlantis_ori/mqtt/__init__.py
aquatlantis_ori/mqtt/client.py
aquatlantis_ori/mqtt/const.py
aquatlantis_ori/mqtt/models.py
aquatlantis_ori-0.0.12.dist-info/METADATA
aquatlantis_ori-0.0.12.dist-info/WHEEL
aquatlantis_ori-0.0.12.dist-info/licenses/LICENSE
aquatlantis_ori-0.0.12.dist-info/RECORD
