Metadata-Version: 2.4
Name: aquatlantis-ori
Version: 0.0.12
Summary: Asynchronous Python client for Aquatlantis Ori Smart Controller
Project-URL: Documentation, https://github.com/golles/python-aquatlantis-ori
Project-URL: Homepage, https://github.com/golles/python-aquatlantis-ori
Project-URL: Repository, https://github.com/golles/python-aquatlantis-ori
Project-URL: Issues, https://github.com/golles/python-aquatlantis-ori/issues
Author-email: Sander Gols <developer@golles.nl>
License-Expression: MIT
License-File: LICENSE
Classifier: Development Status :: 3 - Alpha
Classifier: Framework :: AsyncIO
Classifier: Intended Audience :: Developers
Classifier: License :: OSI Approved :: MIT License
Classifier: Natural Language :: English
Classifier: Operating System :: OS Independent
Classifier: Programming Language :: Python :: 3
Classifier: Programming Language :: Python :: 3.13
Classifier: Topic :: Software Development :: Libraries :: Python Modules
Requires-Python: <3.14,>=3.13
Requires-Dist: aiohttp>=3.12.0
Requires-Dist: mashumaro>=3.16
Requires-Dist: orjson>=3.10.0
Requires-Dist: paho-mqtt>=2.1.0
